xornlpcrack/__init__.py
xornlpcrack/__main__.py
xornlpcrack-0.1.2.dist-info/METADATA
xornlpcrack-0.1.2.dist-info/WHEEL
xornlpcrack-0.1.2.dist-info/entry_points.txt
xornlpcrack-0.1.2.dist-info/top_level.txt
xornlpcrack-0.1.2.dist-info/RECORD
